shgod/__init__.py
shgod/__main__.py
shgod/cli.py
shgod/config.py
shgod/templating.py
shgod/test_e2e.py
shgod/test_lex.py
shgod/test_templating.py
shgod/test_tooling.py
shgod/tmux.py
shgod/tooling.py
shgod-0.1.0.dist-info/METADATA
shgod-0.1.0.dist-info/WHEEL
shgod-0.1.0.dist-info/entry_points.txt
shgod-0.1.0.dist-info/top_level.txt
shgod-0.1.0.dist-info/RECORD
