Metadata-Version: 2.4
Name: shgod
Version: 0.1.0
Summary: Add your description here
Project-URL: Homepage, https://github.com/samuelstevens/shgod
Project-URL: Issues, https://github.com/samuelstevens/shgod/issues
Requires-Python: >=3.12
Requires-Dist: beartype>=0.20.2
Requires-Dist: litellm>=1.70.0
Requires-Dist: rich>=14.0.0
Requires-Dist: tyro>=0.9.20
